agentflow/__init__.py
agentflow/cli.py
agentflow/config/__init__.py
agentflow/config/database.py
agentflow/config/settings.py
agentflow/db/__init__.py
agentflow/db/base.py
agentflow/db/session.py
agentflow/db/test_connection.py
agentflow/entities/__init__.py
agentflow/entities/action.py
agentflow/entities/commit.py
agentflow/entities/session.py
agentflow/entities/workspace.py
agentflow/utils/__init__.py
agentflow/utils/formatters.py
agentflow/utils/id_generator.py
agentflow/utils/state.py
agentflow_cli-0.1.0.dist-info/licenses/LICENSE
agentflow_cli-0.1.0.dist-info/METADATA
agentflow_cli-0.1.0.dist-info/WHEEL
agentflow_cli-0.1.0.dist-info/entry_points.txt
agentflow_cli-0.1.0.dist-info/top_level.txt
agentflow_cli-0.1.0.dist-info/RECORD
