Metadata-Version: 2.4
Name: agentflow-cli
Version: 0.1.0
Summary: Git-like workflow management for AI agents
Author-email: Developers Secrets Inc <contact@developers-secrets.com>
License-Expression: MIT
Project-URL: Homepage, https://github.com/Developers-Secrets-Inc/agentflow
Project-URL: Repository, https://github.com/Developers-Secrets-Inc/agentflow
Project-URL: Issues, https://github.com/Developers-Secrets-Inc/agentflow/issues
Keywords: git,workflow,ai,agent,cli,version-control,session-tracking
Classifier: Development Status :: 4 - Beta
Classifier: Environment :: Console
Classifier: Intended Audience :: Developers
Classifier: Programming Language :: Python :: 3
Classifier: Programming Language :: Python :: 3.14
Classifier: Programming Language :: Python :: 3.15
Classifier: Topic :: Software Development :: Version Control
Classifier: Topic :: Utilities
Requires-Python: >=3.14
License-File: LICENSE
Requires-Dist: typer>=0.12.0
Requires-Dist: sqlalchemy>=2.0.0
Requires-Dist: asyncpg>=0.29.0
Requires-Dist: alembic>=1.13.0
Requires-Dist: pydantic>=2.0.0
Requires-Dist: pydantic-settings>=2.0.0
Requires-Dist: rich>=13.0.0
Requires-Dist: python-dateutil>=2.8.0
Requires-Dist: questionary>=2.1.1
Provides-Extra: dev
Requires-Dist: pytest>=8.0.0; extra == "dev"
Requires-Dist: pytest-asyncio>=0.23.0; extra == "dev"
Requires-Dist: aiosqlite>=0.19.0; extra == "dev"
Requires-Dist: mypy>=1.0.0; extra == "dev"
Requires-Dist: ruff>=0.1.0; extra == "dev"
Dynamic: license-file
